pepedp/__init__.py
pepedp/enum.py
pepedp/torch_enum.py
pepedp/embedding/__init__.py
pepedp/embedding/convnext.py
pepedp/embedding/embedding_class.py
pepedp/embedding/enum.py
pepedp/scripts/__init__.py
pepedp/scripts/archs/ICNet.py
pepedp/scripts/archs/__init__.py
pepedp/scripts/archs/blocklines.py
pepedp/scripts/iqa/IC9600_iqa.py
pepedp/scripts/iqa/__init__.py
pepedp/scripts/iqa/aniqa.py
pepedp/scripts/iqa/blocklines_iqa.py
pepedp/scripts/iqa/hyper_iqa.py
pepedp/scripts/iqa/topiq.py
pepedp/scripts/utils/__init__.py
pepedp/scripts/utils/best_tile.py
pepedp/scripts/utils/deduplicate.py
pepedp/scripts/utils/distance.py
pepedp/scripts/utils/module.py
pepedp/scripts/utils/objects.py
pepedp/scripts/utils/video_to_frames.py
pepedp/scripts/utils/complexity/__init__.py
pepedp/scripts/utils/complexity/ic9600.py
pepedp/scripts/utils/complexity/laplacian.py
pepedp/scripts/utils/complexity/object.py
pepedp-0.1.0.dist-info/licenses/LICENSE
pepedp-0.1.0.dist-info/METADATA
pepedp-0.1.0.dist-info/WHEEL
pepedp-0.1.0.dist-info/top_level.txt
pepedp-0.1.0.dist-info/RECORD
