Metadata-Version: 2.4
Name: pepedp
Version: 0.1.0
Summary: Add your description here
License-Expression: MIT
Requires-Python: >=3.13
License-File: LICENSE
Requires-Dist: llvmlite>=0.44.0
Requires-Dist: numba>=0.61.2
Requires-Dist: numpy>=2.2
Requires-Dist: opencv-python>=4.11.0.86
Requires-Dist: pepeline==1.0.0
Requires-Dist: pyiqa
Requires-Dist: tqdm>=4.67.1
Dynamic: license-file
